Metadata-Version: 2.1
Name: samp-data-generation
Version: 1.0.8
Summary: This python library handles synthetic data generation for the Omdena-SAMP project.
Home-page: UNKNOWN
Author: Samuel Nnitiwe Theophilus
Author-email: nnitiwe@gmail.com
License: MIT
Keywords: object detection,synthetic data
Platform: UNKNOWN
Classifier: Development Status :: 5 - Production/Stable
Classifier: Intended Audience :: Developers
Classifier: Topic :: Software Development :: Build Tools
Classifier: License :: OSI Approved :: MIT License
Classifier: Programming Language :: Python :: 3
Classifier: Programming Language :: Python :: 3.4
Classifier: Programming Language :: Python :: 3.5
Classifier: Programming Language :: Python :: 3.6
License-File: LICENCE.txt
